nacha/__init__.py
nacha/nacha2_init.py
nacha/nacha3_init.py
nacha/packages/__init__.py
nacha/packages/bryl.py
nacha/packages/bryl3.py
nacha3-0.0.2.dist-info/LICENSE
nacha3-0.0.2.dist-info/METADATA
nacha3-0.0.2.dist-info/WHEEL
nacha3-0.0.2.dist-info/top_level.txt
nacha3-0.0.2.dist-info/RECORD
