Metadata-Version: 2.1
Name: nacha3
Version: 0.0.2
Summary: NACHA File Generation
Home-page: https://github.com/rockxraj68/nacha3.git
Author: Rajendra Gupta
Author-email: roy.gupta68@gmail.com
License: UNKNOWN
Platform: any
Classifier: Development Status :: 4 - Beta
Classifier: Intended Audience :: Developers
Classifier: Natural Language :: English
Classifier: License :: OSI Approved :: ISC License (ISCL)
Classifier: Programming Language :: Python
Classifier: Programming Language :: Python :: 3.6
Requires-Dist: bryl
Provides-Extra: tests
Requires-Dist: pytest (<3.0,>=2.5) ; extra == 'tests'
Requires-Dist: pytest-cov (<2.0,>=1.7) ; extra == 'tests'
Requires-Dist: unittest2 (<0.6,>=0.5.1) ; extra == 'tests'
